LICENSE
MANIFEST.in
README.md
README.rst
requirements.txt
setup.py
doc/text2datetime.html
text2datetime/__init__.py
text2datetime.egg-info/PKG-INFO
text2datetime.egg-info/SOURCES.txt
text2datetime.egg-info/dependency_links.txt
text2datetime.egg-info/requires.txt
text2datetime.egg-info/top_level.txt