Metadata-Version: 1.1
Name: text2datetime
Version: 1.0.1
Summary: Python module which can convert an extensive number of ways to represent time with strings to datetime objects
Home-page: https://github.com/kata198/text2datetime
Author: Tim Savannah
Author-email: kata198@gmail.com
License: LGPLv2
Keywords: text2datetime,text,string,time,conversion,datetime,tomorrow,relative,date,convert
Platform: UNKNOWN
Classifier: Development Status :: 5 - Production/Stable
Classifier: Programming Language :: Python
Classifier: License :: OSI Approved :: GNU Lesser General Public License v2 (LGPLv2)
Classifier: Programming Language :: Python :: 2
Classifier: Programming Language :: Python :: 2.7
Classifier: Programming Language :: Python :: 3
Classifier: Programming Language :: Python :: 3.4
Classifier: Programming Language :: Python :: 3.5
Provides: text2datetime
